oncodrivefml/mtc.py
oncodrivefml/walker_cython.pyx
oncodrivefml/indels.py
oncodrivefml/oncodrivefml.py
oncodrivefml/oncodrivefml_v2.conf.template.spec
oncodrivefml/exome.json.gz
oncodrivefml/signature.py
oncodrivefml/walker_cython.cpython-39-x86_64-linux-gnu.so
oncodrivefml/walker.py
oncodrivefml/reference.py
oncodrivefml/oncodrivefml_v2.conf.template
oncodrivefml/walker_cython.cpython-38-x86_64-linux-gnu.so
oncodrivefml/store.py
oncodrivefml/config.py
oncodrivefml/load.py
oncodrivefml/ensembl_genes_75.txt.gz
oncodrivefml/stats.py
oncodrivefml/scores.py
oncodrivefml/__init__.py
oncodrivefml/utils.py
oncodrivefml/genome.json.gz
oncodrivefml/error.py
oncodrivefml/main.py
oncodrivefml/walker_cython.cpython-311-x86_64-linux-gnu.so
oncodrivefml/executors/sig2probs.py
oncodrivefml/executors/element.py
oncodrivefml/executors/bymutation.py
oncodrivefml/executors/__init__.py
oncodrivefml/executors/bysample.py
extra/triplets.py
extra/stops.py
oncodrivefml-2.5.0.dist-info/WHEEL
oncodrivefml-2.5.0.dist-info/RECORD
oncodrivefml-2.5.0.dist-info/entry_points.txt
oncodrivefml-2.5.0.dist-info/METADATA
oncodrivefml-2.5.0.dist-info/licenses/LICENSE
