Metadata-Version: 2.4
Name: oncodrivefml
Version: 2.5.0
Summary: Identify signals of positive selection in somatic mutations
Project-URL: Download, https://pypi.org/project/oncodrivefml/#history
Project-URL: Homepage, https://github.com/bbglab/oncodrivefml
Author-email: "BBGLab (Barcelona Biomedical Genomics Lab)" <bbglab@irbbarcelona.org>
License: ﻿OncodriveFML is the property of the Universitat Pompeu Fabra (UPF), which hold the copyright thereto.
License-File: LICENSE
Requires-Python: <3.12.0,>=3.8.0
Requires-Dist: ago==0.0.93
Requires-Dist: bgcache==0.1
Requires-Dist: bgconfig==0.10
Requires-Dist: bgdata>=2.0.4
Requires-Dist: bglogs==0.6
Requires-Dist: bgparsers==0.10
Requires-Dist: bgreference==0.6
Requires-Dist: bgsignature==0.2
Requires-Dist: bokeh==1.4.0
Requires-Dist: click==8.0.4
Requires-Dist: intervaltree==3.1.0
Requires-Dist: jinja2==3.0.3
Requires-Dist: matplotlib==3.6.3
Requires-Dist: numpy==1.24.4
Requires-Dist: pandas==1.5.3
Requires-Dist: pytabix==0.1
Requires-Dist: scipy==1.10.1
Requires-Dist: statsmodels==0.14.0
